
   [
        {
            "id": 1,
            "avatar": "https://www.hijabistahub.com/scripts/timthumb.php?src=https://www.hijabistahub.com/site_media/img/0L7A9475_20220329223244.jpg&w=500&zc=1",
            "title": "DIANNA KURUNG FOR KIDS (AQUA BLUE)",
            "price": "159.000",
            "size": [
                "1 - 2", "7 - 8"
            ]

        },
        {
            "id": 2,
            "avatar": "https://www.hijabistahub.com/scripts/timthumb.php?src=https://www.hijabistahub.com/site_media/img/0L7A9208_20220329223501.jpg&w=500&zc=1",
            "title": "DIANNA KURUNG FOR KIDS (BLACK)",
            "price": "177.000",
            "size": [
                "1 - 2", "7 - 8", "16 - 17"
            ]

        },
        {
            "id": 3,
            "avatar": "https://www.hijabistahub.com/scripts/timthumb.php?src=https://www.hijabistahub.com/site_media/img/0L7A9425_20220329223544.jpg&w=500&zc=1",
            "title": "DIANNA KURUNG FOR KIDS (AQUA BLUE)",
            "price": "190.000",
            "size": [
                "7 - 8"
            ]

        },
        {
            "id": 4,
            "avatar": "https://www.hijabistahub.com/scripts/timthumb.php?src=https://www.hijabistahub.com/site_media/img/0L7A9475_20220329223244.jpg&w=500&zc=1",
            "title": "DIANNA KURUNG FOR KIDS (AQUA BLUE)",
            "price": "200.000",
            "size": [
                "1 - 2", "7 - 8", "12 - 13"
            ]

        },
        {
            "id": 5,
            "avatar": "https://www.hijabistahub.com/scripts/timthumb.php?src=https://www.hijabistahub.com/site_media/img/0L7A9518_20220329224012.jpg&w=500&zc=1",
            "title": "DIANNA KURUNG FOR KIDS (AQUA BLUE)",
            "price": "159.000",
            "size": [
                "1 - 2", "7 - 8"
            ]

        },
        {
            "id": 6,
            "avatar": "https://www.hijabistahub.com/scripts/timthumb.php?src=https://www.hijabistahub.com/site_media/img/0L7A9371_20220330095704.jpg&w=500&zc=1",
            "title": "DIANNA KURUNG FOR KIDS (BLACK)",
            "price": "177.000",
            "size": [
                "1 - 2", "7 - 8", "16 - 17"
            ]

        },
        {
            "id": 7,
            "avatar": "https://www.hijabistahub.com/scripts/timthumb.php?src=https://www.hijabistahub.com/site_media/img/0L7A9475_20220329223244.jpg&w=500&zc=1",
            "title": "DIANNA KURUNG FOR KIDS (AQUA BLUE)",
            "price": "190.000",
            "size": [
                "7 - 8"
            ]

        },
        {
            "id": 8,
            "avatar": "https://www.hijabistahub.com/scripts/timthumb.php?src=https://www.hijabistahub.com/site_media/img/0L7A9475_20220329223244.jpg&w=500&zc=1",
            "title": "DIANNA KURUNG FOR KIDS (AQUA BLUE)",
            "price": "200.000",
            "size": [
                "1 - 2", "7 - 8", "12 - 13"
            ]

        }
    ]
